tednet/__init__.py
tednet/_ops.py
tednet/tnn/__init__.py
tednet/tnn/initializer.py
tednet/tnn/tn_cnn.py
tednet/tnn/tn_linear.py
tednet/tnn/tn_module.py
tednet/tnn/tn_rnn.py
tednet/tnn/bt_tucker/__init__.py
tednet/tnn/bt_tucker/base.py
tednet/tnn/bt_tucker/btt_lenet.py
tednet/tnn/bt_tucker/btt_resnet.py
tednet/tnn/bt_tucker/btt_rnn.py
tednet/tnn/cp/__init__.py
tednet/tnn/cp/base.py
tednet/tnn/cp/cp_lenet.py
tednet/tnn/cp/cp_resnet.py
tednet/tnn/cp/cp_rnn.py
tednet/tnn/tensor_ring/__init__.py
tednet/tnn/tensor_ring/base.py
tednet/tnn/tensor_ring/tr_lenet.py
tednet/tnn/tensor_ring/tr_resnet.py
tednet/tnn/tensor_ring/tr_rnn.py
tednet/tnn/tensor_train/__init__.py
tednet/tnn/tensor_train/base.py
tednet/tnn/tensor_train/tt_lenet.py
tednet/tnn/tensor_train/tt_resnet.py
tednet/tnn/tensor_train/tt_rnn.py
tednet/tnn/tucker2/__init__.py
tednet/tnn/tucker2/base.py
tednet/tnn/tucker2/tk2_lenet.py
tednet/tnn/tucker2/tk2_resnet.py
tednet/tnn/tucker2/tk2_rnn.py
tednet-0.1.3.dist-info/LICENSE
tednet-0.1.3.dist-info/METADATA
tednet-0.1.3.dist-info/WHEEL
tednet-0.1.3.dist-info/top_level.txt
tednet-0.1.3.dist-info/RECORD
