Metadata-Version: 2.1
Name: tednet
Version: 0.1.3
Summary: tednet: a framework of tensor decomposition network.
Home-page: https://github.com/perryuu/tednet
Author: Perry
Maintainer: Perry
License: MIT
Platform: any
Requires-Dist: torch (>=1.0.0)
